{
  "kind": "collectionType",
  "collectionName": "pages",
  "info": {
    "singularName": "page",
    "pluralName": "pages",
    "displayName": "Page"
  },
  "options": {
    "draftAndPublish": true
  },
  "pluginOptions": {},
  "attributes": {
    "title": {
      "type": "string",
      "required": true
    },
    "slug": {
      "type": "string",
      "required": true,
      "unique": true
    },
    "content": {
      "type": "dynamiczone",
      "components": ["content.image-texts", "content.accordion"]
    }
  }
}
