{
  "homepage": {
    "title": "Rediscover to renew",
    "content": [
      {
        "__component": "content.image-texts",
        "direction": "odd",
        "images": [
          {
            "__component": "content.image-text",
            "title": "Waar ga jij beginnen?",
            "subtitle": "Creative Digital Agency",
            "description": "EF2 maakt jouw verbeterslag realiteit. Wij helpen je op een pragmatische manier, met een compleet plan. Gebaseerd op eenvoud. Eerst kijken wat er goed gaat. Kansen inventariseren. Dan maken we een sprong vooruit. Zo kun jij groeien vanuit je bestaande, solide basis. Dat is Rediscover to Renew!",
            "buttonText": "Onze expertises",
            "href": "#"
          }
        ]
      }
    ]
  }
}
